turtle_trading/__init__.py
turtle_trading/__version__.py
turtle_trading/_config/__init__.py
turtle_trading/_config/breakout.py
turtle_trading/_config/exceptions.py
turtle_trading/_config/rules.txt
turtle_trading/_config/utils.py
turtle_trading/_data/__init__.py
turtle_trading/_data/dataframe_loader.py
turtle_trading/_data/futures_query.py
turtle_trading/entries/__init__.py
turtle_trading/entries/add_units.py
turtle_trading/entries/last_breakout.py
turtle_trading/entries/system.py
turtle_trading/exits/__init__.py
turtle_trading/exits/exits.py
turtle_trading/position_sizing/__init__.py
turtle_trading/position_sizing/exceptions.py
turtle_trading/position_sizing/algorithms/__init__.py
turtle_trading/position_sizing/algorithms/get_n.py
turtle_trading/position_sizing/algorithms/get_unit_size.py
turtle_trading/stops/__init__.py
turtle_trading/stops/stops.py
turtle_trading-3.5.1.dist-info/METADATA
turtle_trading-3.5.1.dist-info/WHEEL
turtle_trading-3.5.1.dist-info/licenses/LICENSE
turtle_trading-3.5.1.dist-info/RECORD
