Metadata-Version: 2.1
Name: turtle-trading
Version: 3.5.1
Summary: A collection of investment tools used by the Turtle Traders.
Project-URL: Homepage, https://github.com/gabekutner/turtle-trading/
Author-email: Gabe Kutner <gabekutner1@gmail.com>
License: MIT License
License-File: LICENSE
Keywords: investing,python,trading,turtle,turtle-trading
Classifier: Intended Audience :: Developers
Classifier: License :: OSI Approved :: MIT License
Classifier: Programming Language :: Python :: 3
Classifier: Programming Language :: Python :: 3 :: Only
Classifier: Topic :: Software Development :: Libraries
Requires-Python: >=3.8
Requires-Dist: pandas
Requires-Dist: yahoo-fin>=0.8.9.1
